<Properties StartupConfiguration="{93FFF9DD-EC03-4EFD-8A95-009677C328E6}|Default">
  <MonoDevelop.Ide.Workbench ActiveDocument="Ch03Ex01/Program.cs">
    <Files>
      <File FileName="Ch03Ex01/App.config" Line="1" Column="1" />
      <File FileName="Ch03Ex01/Program.cs" Line="22" Column="1" />
    </Files>
    <Pads>
      <Pad Id="ProjectPad">
        <State name="__root__">
          <Node name="Ch03Ex01" expanded="True">
            <Node name="Ch03Ex01" expanded="True">
              <Node name="Program.cs" selected="True" />
            </Node>
          </Node>
        </State>
      </Pad>
      <Pad Id="ClassPad">
        <State name="__root__">
          <Node name="Ch03Ex01" expanded="True" selected="True" />
        </State>
      </Pad>
      <Pad Id="MonoDevelop.Debugger.WatchPad">
        <State />
      </Pad>
    </Pads>
  </MonoDevelop.Ide.Workbench>
  <MonoDevelop.Ide.Workspace ActiveConfiguration="Debug" />
  <MonoDevelop.Ide.DebuggingService.Breakpoints>
    <BreakpointStore />
  </MonoDevelop.Ide.DebuggingService.Breakpoints>
  <MonoDevelop.Ide.DebuggingService.PinnedWatches />
  <MonoDevelop.Ide.ItemProperties.Ch03Ex01 PreferredExecutionTarget="MonoDevelop.Default" />
  <MultiItemStartupConfigurations />
</Properties>